polling.py
polling-0.3.0.dist-info/LICENSE.md
polling-0.3.0.dist-info/METADATA
polling-0.3.0.dist-info/WHEEL
polling-0.3.0.dist-info/top_level.txt
polling-0.3.0.dist-info/RECORD
